LICENSE
MANIFEST.in
README.md
git-qdiff
git_qdiff.py
setup.py
git_qdiff.egg-info/PKG-INFO
git_qdiff.egg-info/SOURCES.txt
git_qdiff.egg-info/dependency_links.txt
git_qdiff.egg-info/top_level.txt