Metadata-Version: 1.0
Name: git-qdiff
Version: 0.1.2
Summary: Bzr tool's qdiff for git
Home-page: https://github.com/amigrave/git-qdiff
Author: Fabien Meghazi
Author-email: agr@amigrave.com
License: MIT
Keywords: git qdiff bzr diff
Platform: UNKNOWN
